[
    {
        "key": "dbln",
        "value": "%7B%22100005113782220%22%3A%22XYwfO91A%22%2C%2261557729897412%22%3A%22cLbzTXeS%22%7D",
        "domain": "facebook.com",
        "path": "/login/device-based/",
        "hostOnly": false,
        "creation": "2025-03-21T06:00:46.740Z",
        "lastAccessed": "2025-03-21T06:00:46.740Z"
    },
    {
        "key": "sb",
        "value": "iqg5Z_qmesSKv4srY2aNTk4R",
        "domain": "facebook.com",
        "path": "/",
        "hostOnly": false,
        "creation": "2025-03-21T06:00:46.740Z",
        "lastAccessed": "2025-03-21T06:00:46.740Z"
    },
    {
        "key": "vpd",
        "value": "v1%3B791x412x1.75",
        "domain": "facebook.com",
        "path": "/",
        "hostOnly": false,
        "creation": "2025-03-21T06:00:46.740Z",
        "lastAccessed": "2025-03-21T06:00:46.740Z"
    },
    {
        "key": "ps_l",
        "value": "1",
        "domain": "facebook.com",
        "path": "/",
        "hostOnly": false,
        "creation": "2025-03-21T06:00:46.740Z",
        "lastAccessed": "2025-03-21T06:00:46.740Z"
    },
    {
        "key": "ps_n",
        "value": "1",
        "domain": "facebook.com",
        "path": "/",
        "hostOnly": false,
        "creation": "2025-03-21T06:00:46.740Z",
        "lastAccessed": "2025-03-21T06:00:46.740Z"
    },
    {
        "key": "dpr",
        "value": "1.9240320920944214",
        "domain": "facebook.com",
        "path": "/",
        "hostOnly": false,
        "creation": "2025-03-21T06:00:46.740Z",
        "lastAccessed": "2025-03-21T06:00:46.740Z"
    },
    {
        "key": "locale",
        "value": "en_GB",
        "domain": "facebook.com",
        "path": "/",
        "hostOnly": false,
        "creation": "2025-03-21T06:00:46.740Z",
        "lastAccessed": "2025-03-21T06:00:46.740Z"
    },
    {
        "key": "datr",
        "value": "aE7ZZysgfkl9udwgDGYi9kHi",
        "domain": "facebook.com",
        "path": "/",
        "hostOnly": false,
        "creation": "2025-03-21T06:00:46.740Z",
        "lastAccessed": "2025-03-21T06:00:46.740Z"
    },
    {
        "key": "wd",
        "value": "412x791",
        "domain": "facebook.com",
        "path": "/",
        "hostOnly": false,
        "creation": "2025-03-21T06:00:46.740Z",
        "lastAccessed": "2025-03-21T06:00:46.740Z"
    },
    {
        "key": "c_user",
        "value": "61557729897412",
        "domain": "facebook.com",
        "path": "/",
        "hostOnly": false,
        "creation": "2025-03-21T06:00:46.740Z",
        "lastAccessed": "2025-03-21T06:00:46.740Z"
    },
    {
        "key": "fr",
        "value": "1KcrhghivLo86bIsM.AWWdHWw4Dg5EccIARHfaul1PeFz7F9zEeqV9Cg.Bn1xYD..AAA.0.0.Bn2hQK.AWXk1r1mnVE",
        "domain": "facebook.com",
        "path": "/",
        "hostOnly": false,
        "creation": "2025-03-21T06:00:46.740Z",
        "lastAccessed": "2025-03-21T06:00:46.740Z"
    },
    {
        "key": "xs",
        "value": "34%3AVhnSFkANs51EZg%3A2%3A1742345227%3A-1%3A5179",
        "domain": "facebook.com",
        "path": "/",
        "hostOnly": false,
        "creation": "2025-03-21T06:00:46.740Z",
        "lastAccessed": "2025-03-21T06:00:46.740Z"
    },
    {
        "key": "wl_cbv",
        "value": "v2%3Bclient_version%3A2764%3Btimestamp%3A1742536831",
        "domain": "facebook.com",
        "path": "/",
        "hostOnly": false,
        "creation": "2025-03-21T06:00:46.740Z",
        "lastAccessed": "2025-03-21T06:00:46.740Z"
    },
    {
        "key": "fbl_st",
        "value": "101531410%3BT%3A29042280",
        "domain": "facebook.com",
        "path": "/",
        "hostOnly": false,
        "creation": "2025-03-21T06:00:46.740Z",
        "lastAccessed": "2025-03-21T06:00:46.740Z"
    }
]
